wordcount_demo/__init__.py
wordcount_demo/plotting.py
wordcount_demo/wordcount_demo.py
wordcount_demo-0.1.0.dist-info/LICENSE
wordcount_demo-0.1.0.dist-info/WHEEL
wordcount_demo-0.1.0.dist-info/METADATA
wordcount_demo-0.1.0.dist-info/RECORD
