Metadata-Version: 2.1
Name: wordcount-demo
Version: 0.1.0
Summary: A demo for creating a word count package
License: MIT
Author: Nick_Mao
Requires-Python: >=3.9,<4.0
Classifier: License :: OSI Approved :: MIT License
Classifier: Programming Language :: Python :: 3
Classifier: Programming Language :: Python :: 3.9
Requires-Dist: matplotlib (>=3.5.1,<4.0.0)
